
<annotation>
    <folder>images</folder>
    <filename>boat565.png</filename>
    <size>
        <width>400</width>
        <height>356</height>
        <depth>3</depth>
    </size>
    <segmented>0</segmented>
    <object>
        <name>boat</name>
        <pose>Unspecified</pose>
        <truncated>0</truncated>
        <occluded>0</occluded>
        <difficult>0</difficult>
        <bndbox>
            <xmin>268</xmin>
            <ymin>255</ymin>
            <xmax>272</xmax>
            <ymax>259</ymax>
        </bndbox>
    </object>
    <object>
        <name>boat</name>
        <pose>Unspecified</pose>
        <truncated>0</truncated>
        <occluded>0</occluded>
        <difficult>0</difficult>
        <bndbox>
            <xmin>120</xmin>
            <ymin>168</ymin>
            <xmax>124</xmax>
            <ymax>172</ymax>
        </bndbox>
    </object>
</annotation>