
<annotation>
    <folder>images</folder>
    <filename>boat331.png</filename>
    <size>
        <width>512</width>
        <height>482</height>
        <depth>3</depth>
    </size>
    <segmented>0</segmented>
    <object>
        <name>boat</name>
        <pose>Unspecified</pose>
        <truncated>0</truncated>
        <occluded>0</occluded>
        <difficult>0</difficult>
        <bndbox>
            <xmin>195</xmin>
            <ymin>117</ymin>
            <xmax>343</xmax>
            <ymax>260</ymax>
        </bndbox>
    </object>
</annotation>